addressValidator/__init__.py
addressValidator/mealy.py
addressValidator/validator.py
addressValidator-1.2.2.dist-info/LICENSE
addressValidator-1.2.2.dist-info/METADATA
addressValidator-1.2.2.dist-info/WHEEL
addressValidator-1.2.2.dist-info/top_level.txt
addressValidator-1.2.2.dist-info/RECORD
